Metadata-Version: 2.4
Name: polygraph-benchmark
Version: 1.0.2
Summary: Evaluation benchmarks for graph generative models
Author-email: Markus Krimmel <krimmel@biochem.mpg.de>, Philip Hartout <hartout@biochem.mpg.de>, Dexiong Chen <dchen@biochem.mpg.de>, Karsten Borgwardt <borgwardt@biochem.mpg.de>
Requires-Python: >=3.9
License-File: LICENSE
Requires-Dist: numpy<3.0,>=1.26.4
Requires-Dist: torch<3.0,>=2.4.0
Requires-Dist: torch_geometric<3.0,>=2.6.1
Requires-Dist: rich
Requires-Dist: scipy<2.0,>=1.12.0
Requires-Dist: pydantic~=2.11.7
Requires-Dist: networkx<4.0,>=3.2
Requires-Dist: joblib
Requires-Dist: appdirs
Requires-Dist: loguru
Requires-Dist: rdkit
Requires-Dist: pandas
Requires-Dist: orbit-count
Requires-Dist: numba<0.62.0,>=0.60.0
Requires-Dist: scikit-learn<2.0,>=1.6.1
Requires-Dist: tabpfn==2.0.9
Requires-Dist: fcd~=1.2.2
Provides-Extra: dev
Requires-Dist: pytest; extra == "dev"
Requires-Dist: pytest-xdist; extra == "dev"
Requires-Dist: pyprojroot; extra == "dev"
Requires-Dist: ipython; extra == "dev"
Requires-Dist: ruff; extra == "dev"
Requires-Dist: pre-commit; extra == "dev"
Requires-Dist: ipykernel; extra == "dev"
Requires-Dist: grakel; extra == "dev"
Requires-Dist: pytest-profiling; extra == "dev"
Requires-Dist: mkdocs; extra == "dev"
Requires-Dist: mkdocstrings; extra == "dev"
Requires-Dist: mkdocs-material; extra == "dev"
Requires-Dist: mkdocstrings-python; extra == "dev"
Requires-Dist: mkdocs-terminal; extra == "dev"
Requires-Dist: tabulate; extra == "dev"
Requires-Dist: jinja2; extra == "dev"
Requires-Dist: seaborn; extra == "dev"
Requires-Dist: tueplots; extra == "dev"
Requires-Dist: typer; extra == "dev"
Dynamic: license-file
